csv_summary/__init__.py
csv_summary/cli.py
csv_summary_cli-0.1.0.dist-info/licenses/LICENSE
csv_summary_cli-0.1.0.dist-info/METADATA
csv_summary_cli-0.1.0.dist-info/WHEEL
csv_summary_cli-0.1.0.dist-info/entry_points.txt
csv_summary_cli-0.1.0.dist-info/top_level.txt
csv_summary_cli-0.1.0.dist-info/RECORD
