Metadata-Version: 2.4
Name: csv-summary-cli
Version: 0.1.0
Summary: A CLI tool to summarize CSV files with basic stats
Author-email: Madhur Dixit <madhurdixit37@gmail.com>
License-Expression: MIT
License-File: LICENSE
Dynamic: license-file
